toothfairyai/__init__.py
toothfairyai/client.py
toothfairyai/errors.py
toothfairyai/py.typed
toothfairyai/types.py
toothfairyai/agent_functions/__init__.py
toothfairyai/agent_functions/agent_functions_manager.py
toothfairyai/agents/__init__.py
toothfairyai/agents/agent_manager.py
toothfairyai/authorisations/__init__.py
toothfairyai/authorisations/authorisations_manager.py
toothfairyai/benchmarks/__init__.py
toothfairyai/benchmarks/benchmarks_manager.py
toothfairyai/billing/__init__.py
toothfairyai/billing/billing_manager.py
toothfairyai/channels/__init__.py
toothfairyai/channels/channels_manager.py
toothfairyai/charting_settings/__init__.py
toothfairyai/charting_settings/charting_settings_manager.py
toothfairyai/chat/__init__.py
toothfairyai/chat/chat_manager.py
toothfairyai/connections/__init__.py
toothfairyai/connections/connections_manager.py
toothfairyai/dictionary/__init__.py
toothfairyai/dictionary/dictionary_manager.py
toothfairyai/documents/__init__.py
toothfairyai/documents/document_manager.py
toothfairyai/embeddings/__init__.py
toothfairyai/embeddings/embeddings_manager.py
toothfairyai/embeddings_settings/__init__.py
toothfairyai/embeddings_settings/embeddings_settings_manager.py
toothfairyai/entities/__init__.py
toothfairyai/entities/entity_manager.py
toothfairyai/folders/__init__.py
toothfairyai/folders/folder_manager.py
toothfairyai/hooks/__init__.py
toothfairyai/hooks/hooks_manager.py
toothfairyai/members/__init__.py
toothfairyai/members/members_manager.py
toothfairyai/prompts/__init__.py
toothfairyai/prompts/prompt_manager.py
toothfairyai/request_logs/__init__.py
toothfairyai/request_logs/request_logs_manager.py
toothfairyai/scheduled_jobs/__init__.py
toothfairyai/scheduled_jobs/scheduled_jobs_manager.py
toothfairyai/secrets/__init__.py
toothfairyai/secrets/secrets_manager.py
toothfairyai/sites/__init__.py
toothfairyai/sites/sites_manager.py
toothfairyai/streaming/__init__.py
toothfairyai/streaming/streaming_manager.py
toothfairyai-0.5.6.dist-info/licenses/LICENSE
toothfairyai-0.5.6.dist-info/METADATA
toothfairyai-0.5.6.dist-info/WHEEL
toothfairyai-0.5.6.dist-info/top_level.txt
toothfairyai-0.5.6.dist-info/RECORD
