Metadata-Version: 2.4
Name: toothfairyai
Version: 0.5.6
Summary: Official Python SDK for ToothFairyAI API
Author-email: ToothFairyAI <support@toothfairyai.com>
License: MIT
Project-URL: Homepage, https://toothfairyai.com
Project-URL: Documentation, https://docs.toothfairyai.com
Project-URL: Repository, https://github.com/toothfairyai/python-sdk
Project-URL: Changelog, https://github.com/toothfairyai/python-sdk/blob/main/CHANGELOG.md
Keywords: toothfairyai,ai,sdk,api,chatbot,agents,llm
Classifier: Development Status :: 4 - Beta
Classifier: Intended Audience :: Developers
Classifier: License :: OSI Approved :: MIT License
Classifier: Operating System :: OS Independent
Classifier: Programming Language :: Python :: 3
Classifier: Programming Language :: Python :: 3.8
Classifier: Programming Language :: Python :: 3.9
Classifier: Programming Language :: Python :: 3.10
Classifier: Programming Language :: Python :: 3.11
Classifier: Programming Language :: Python :: 3.12
Classifier: Topic :: Software Development :: Libraries :: Python Modules
Classifier: Typing :: Typed
Requires-Python: >=3.8
License-File: LICENSE
Requires-Dist: requests>=2.28.0
Provides-Extra: dev
Requires-Dist: pytest>=7.0.0; extra == "dev"
Requires-Dist: pytest-asyncio>=0.21.0; extra == "dev"
Requires-Dist: pytest-cov>=4.0.0; extra == "dev"
Requires-Dist: black>=23.0.0; extra == "dev"
Requires-Dist: isort>=5.12.0; extra == "dev"
Requires-Dist: mypy>=1.0.0; extra == "dev"
Requires-Dist: types-requests>=2.28.0; extra == "dev"
Dynamic: license-file
